gyverhubd/__init__.py
gyverhubd/__main__.py
gyverhubd/_version.py
gyverhubd/context.py
gyverhubd/device.py
gyverhubd/device_utils.py
gyverhubd/errors.py
gyverhubd/events.py
gyverhubd/info.py
gyverhubd/local.py
gyverhubd/server.py
gyverhubd/utils.py
gyverhubd/cli/__init__.py
gyverhubd/cli/new_key.py
gyverhubd/cli/pack.py
gyverhubd/cli/run.py
gyverhubd/filesystem/__init__.py
gyverhubd/filesystem/base.py
gyverhubd/filesystem/mapped.py
gyverhubd/filesystem/mapped_file.py
gyverhubd/filesystem/union.py
gyverhubd/filesystem/vfspath.py
gyverhubd/filesystem/virtual.py
gyverhubd/filesystem/virtual_file.py
gyverhubd/proto/__init__.py
gyverhubd/proto/mqtt.py
gyverhubd/proto/proto.py
gyverhubd/proto/serial.py
gyverhubd/proto/websocket.py
gyverhubd/ui/__init__.py
gyverhubd/ui/base.py
gyverhubd/ui/color.py
gyverhubd/ui/component.py
gyverhubd/ui/layout.py
gyverhubd/ui/components/__init__.py
gyverhubd/ui/components/button.py
gyverhubd/ui/components/controls.py
gyverhubd/ui/components/datetime.py
gyverhubd/ui/components/input.py
gyverhubd/ui/components/prompt_confirm.py
gyverhubd/ui/components/spinner.py
gyverhubd/ui/components/switch.py
gyverhubd/ui/components/tabs.py
gyverhubd/ui/components/text.py
pygyverhubd-0.0.4.dist-info/LICENSE
pygyverhubd-0.0.4.dist-info/METADATA
pygyverhubd-0.0.4.dist-info/WHEEL
pygyverhubd-0.0.4.dist-info/top_level.txt
pygyverhubd-0.0.4.dist-info/RECORD
