Metadata-Version: 2.1
Name: pygyverhubd
Version: 0.0.4
Summary: Python implementation of GyverHub device
Author-email: NekoNekoNyan <me@neko-dev.ru>
License: MIT License
Project-URL: Homepage, https://github.com/neko-neko-nyan/pygyverhubd
Project-URL: Bug Tracker, https://github.com/neko-neko-nyan/pygyverhubd/issues
Classifier: Programming Language :: Python :: 3
Classifier: License :: OSI Approved :: MIT License
Classifier: Operating System :: OS Independent
Requires-Python: >=3.10
License-File: LICENSE
Requires-Dist: aiohttp (~=3.8.4)
Requires-Dist: websockets (~=11.0.3)
Requires-Dist: aiomqtt (~=1.0.0)
Requires-Dist: pycryptodome (~=3.18.0)
Requires-Dist: pyserial-asyncio (~=0.6)
